encoder/__init__.py
encoder/pig_latin.py
encrypter2/__init__.py
encrypter2/pig_latin.py
encrypter2-1.1.0.dist-info/LICENSE
encrypter2-1.1.0.dist-info/METADATA
encrypter2-1.1.0.dist-info/WHEEL
encrypter2-1.1.0.dist-info/top_level.txt
encrypter2-1.1.0.dist-info/RECORD
