Metadata-Version: 2.1
Name: encrypter2
Version: 1.1.0
Summary: This is an encoder package
Author: Kanishk
License-File: LICENSE
Requires-Dist: nltk
